phonexia_speech_to_text_whisper_client.py
phonexia_speech_to_text_whisper_client-1.0.0.dist-info/METADATA
phonexia_speech_to_text_whisper_client-1.0.0.dist-info/WHEEL
phonexia_speech_to_text_whisper_client-1.0.0.dist-info/entry_points.txt
phonexia_speech_to_text_whisper_client-1.0.0.dist-info/RECORD
