Metadata-Version: 2.1
Name: phonexia-speech-to-text-whisper-client
Version: 1.0.0
Summary: Client for communication with Phonexia Speech To Text Whisper Enhanced microservice.
Keywords: grpc,transcription,STT,ASR,speech to text,speech,language,microservice
Author: Phonexia
Author-email: info@phonexia.com
Requires-Python: >=3.8,<4.0
Classifier: Programming Language :: Python :: 3
Classifier: Programming Language :: Python :: 3.8
Classifier: Programming Language :: Python :: 3.9
Classifier: Programming Language :: Python :: 3.10
Classifier: Programming Language :: Python :: 3.11
Classifier: Programming Language :: Python :: 3.12
Requires-Dist: grpcio (>=1.54.0,<2.0.0)
Requires-Dist: phonexia-grpc (>=1.0.0,<2.0.0)
Project-URL: Homepage, https://phonexia.com
Project-URL: Issues, https://phonexia.atlassian.net/servicedesk/customer/portal/15/group/20/create/40
Project-URL: protofiles, https://github.com/phonexia/protofiles
